xfer-0.2.9.dist-info/WHEEL
xfer-0.2.9.dist-info/METADATA
xfer-0.2.9.dist-info/metadata.json
xfer-0.2.9.dist-info/RECORD
xfer-0.2.9.dist-info/top_level.txt
xfer-0.2.9.dist-info/DESCRIPTION.rst
xfer-0.2.9.dist-info/entry_points.txt
xfer-0.2.9.data/scripts/git-xfer
xfer/__init__.py
xfer/__main__.py
xfer/cli.py
