Metadata-Version: 2.0
Name: xfer
Version: 0.2.9
Summary: Git plugin for transferring large files across servers.
Home-page: https://github.com/bprinty/xfer
Author: Blake Printy
Author-email: bprinty@gmail.com
License: Apache-2.0
Keywords: xfer
Platform: UNKNOWN
Classifier: Intended Audience :: Developers
Classifier: License :: OSI Approved :: Apache Software License
Classifier: Natural Language :: English
Classifier: Programming Language :: Python :: 2
Classifier: Programming Language :: Python :: 2.6
Classifier: Programming Language :: Python :: 2.7
Classifier: Programming Language :: Python :: 3
Classifier: Programming Language :: Python :: 3.3
Classifier: Programming Language :: Python :: 3.4
Requires-Dist: paramiko (>=2.0.0)
Requires-Dist: cryptography (>=1.1)
Requires-Dist: gems (>=0.2.0)
Requires-Dist: PyYAML (>=3.12)
Requires-Dist: pyasn1 (>=0.1.7)
